setup.py
django_encrypted_json/__init__.py
django_encrypted_json/fields.py
django_encrypted_json/utils.py
django_encrypted_pgjson.egg-info/PKG-INFO
django_encrypted_pgjson.egg-info/SOURCES.txt
django_encrypted_pgjson.egg-info/dependency_links.txt
django_encrypted_pgjson.egg-info/not-zip-safe
django_encrypted_pgjson.egg-info/pbr.json
django_encrypted_pgjson.egg-info/requires.txt
django_encrypted_pgjson.egg-info/top_level.txt