Metadata-Version: 1.1
Name: django-encrypted-pgjson
Version: 0.2.0
Summary: Encrypted PostgreSQL json field support for Django.
Home-page: https://github.com/LucasRoesler/django-encrypted-json
Author: Lucas Roesler
Author-email: roesler.lucas@gmail.com
License: MIT
Keywords: django,postgresql,pgsql,json,field,encryption
Platform: OS Independent
Classifier: Development Status :: 5 - Production/Stable
Classifier: Framework :: Django
Classifier: Intended Audience :: Developers
Classifier: License :: OSI Approved :: BSD License
Classifier: Operating System :: OS Independent
Classifier: Programming Language :: Python
Classifier: Programming Language :: Python :: 2
Classifier: Programming Language :: Python :: 2.7
Classifier: Programming Language :: Python :: 3
Classifier: Programming Language :: Python :: 3.3
Classifier: Topic :: Internet :: WWW/HTTP
